jsonrpc/__init__.py
jsonrpc/some_file.py
hiveio_jsonrpc-0.1.0.dist-info/METADATA
hiveio_jsonrpc-0.1.0.dist-info/WHEEL
hiveio_jsonrpc-0.1.0.dist-info/RECORD
