Metadata-Version: 2.3
Name: hiveio-jsonrpc
Version: 0.1.0
Summary: Prosta biblioteka przykład (Poetry)
License: MIT
Keywords: example,hello
Author: kmochocki
Author-email: kmochocki@syncad.com
Requires-Python: >=3.10
Classifier: License :: OSI Approved :: MIT License
Classifier: Operating System :: OS Independent
Classifier: Programming Language :: Python :: 3
Classifier: Programming Language :: Python :: 3.10
Classifier: Programming Language :: Python :: 3.11
Classifier: Programming Language :: Python :: 3.12
Classifier: Programming Language :: Python :: 3.13
Project-URL: Repository, https://gitlab.syncad.com/hive/jsonrpc
